uvmono/__init__.py
uvmono/github.py
uvmono/template.py
uvmono/utils.py
uvmono/templates/conftest.py.j2
uvmono/templates/devcontainer.json.j2
uvmono/templates/dockerfile.j2
uvmono/templates/filter.yml.j2
uvmono/templates/package_init.py.j2
uvmono/templates/pyproject.toml.j2
uvmono/templates/tests_init.py.j2
uvmono-0.3.9.dist-info/METADATA
uvmono-0.3.9.dist-info/WHEEL
uvmono-0.3.9.dist-info/entry_points.txt
uvmono-0.3.9.dist-info/licenses/LICENSE
uvmono-0.3.9.dist-info/RECORD
