Metadata-Version: 2.4
Name: uvmono
Version: 0.3.9
Summary: Add your description here
Author-email: Jens Peder Meldgaard <JensPederM@gmail.com>
License: MIT License
License-File: LICENSE
Requires-Python: >=3.11
Requires-Dist: fire>=0.7.0
Requires-Dist: jinja2
Requires-Dist: mergedeep>=1.3.4
Requires-Dist: pre-commit>=4.0.1
Requires-Dist: rich>=13.9.4
Requires-Dist: tomli-w>=1.1.0
